{
    "default_parsed_data_dir": "data",
    "default_sitemap_export_file": "extraction.json",
    "extraction_file": "extraction.json",
    "extractor_options": {
        "article_selector": "page",
        "article_tag": "a",
        "category_selector": "gsection",
        "category_tag": "a",
        "excluded_urls": [
            "https://perekos.net/sections/view/149",
            "https://perekos.net/sections/view/527",
            "https://perekos.net/sections/view/5",
            "https://perekos.net/pages/view/4162"
        ],
        "root_url": "https://perekos.net"
    },
    "pages_cache": {
        "cache": [
            [
                {
                    "title": "Бетонные и железобетонные работы",
                    "url": "https://perekos.net/sections/view/68"
                },
                "data\\Технология строительных процессов\\Бетонные и железобетонные работы\\Бетонные и железобетонные работы.json"
            ],
            [
                {
                    "title": "Буровзрывные и свайные работы",
                    "url": "https://perekos.net/sections/view/65"
                },
                "data\\Технология строительных процессов\\Буровзрывные и свайные работы\\Буровзрывные и свайные работы.json"
            ],
            [
                {
                    "title": "Каменные работы в строительстве",
                    "url": "https://perekos.net/sections/view/109"
                },
                "data\\Технология строительных процессов\\Каменные работы в строительстве\\Каменные работы в строительстве.json"
            ],
            [
                {
                    "title": "Монтаж деревянных конструкций",
                    "url": "https://perekos.net/sections/view/105"
                },
                "data\\Технология строительных процессов\\Монтаж деревянных конструкций\\Монтаж деревянных конструкций.json"
            ],
            [
                {
                    "title": "Монтажные работы в строительстве",
                    "url": "https://perekos.net/sections/view/67"
                },
                "data\\Технология строительных процессов\\Монтажные работы в строительстве\\Монтажные работы в строительстве.json"
            ],
            [
                {
                    "title": "Отделочные работы",
                    "url": "https://perekos.net/sections/view/66"
                },
                "data\\Технология строительных процессов\\Отделочные работы\\Отделочные работы.json"
            ],
            [
                {
                    "title": "Реконструкция зданий и сооружений",
                    "url": "https://perekos.net/sections/view/63"
                },
                "data\\Технология строительных процессов\\Реконструкция зданий и сооружений\\Реконструкция зданий и сооружений.json"
            ],
            [
                {
                    "title": "Водоснабжение и водоотведение в строительстве",
                    "url": "https://perekos.net/sections/view/240"
                },
                "data\\Технология строительных процессов\\Теплогазоснабжение_ вентиляция и водоотведение\\Водоснабжение и водоотведение в строительстве\\Водоснабжение и водоотведение в строительстве.json"
            ],
            [
                {
                    "title": "Теплогазоснабжение и вентиляция в строительстве",
                    "url": "https://perekos.net/sections/view/241"
                },
                "data\\Технология строительных процессов\\Теплогазоснабжение_ вентиляция и водоотведение\\Теплогазоснабжение и вентиляция в строительстве\\Теплогазоснабжение и вентиляция в строительстве.json"
            ],
            [
                {
                    "title": "Земляные работы в строительстве",
                    "url": "https://perekos.net/sections/view/69"
                },
                "data\\Технология строительных процессов\\Земляные работы в строительстве\\Земляные работы в строительстве.json"
            ],
            [
                {
                    "title": "Кровельные работы",
                    "url": "https://perekos.net/sections/view/64"
                },
                "data\\Технология строительных процессов\\Кровельные работы\\Кровельные работы.json"
            ],
            [
                {
                    "title": "История развития монолитного строительства",
                    "url": "https://perekos.net/pages/view/1285"
                },
                "data\\Технология строительных процессов\\Монолитное домостроение\\История развития монолитного строительства.json"
            ],
            [
                {
                    "title": "Конструктивные системы и конструкции монолитных зданий",
                    "url": "https://perekos.net/pages/view/1286"
                },
                "data\\Технология строительных процессов\\Монолитное домостроение\\Конструктивные системы и конструкции монолитных зданий.json"
            ],
            [
                {
                    "title": "Опалубка. Классификация, области применения и конструкции",
                    "url": "https://perekos.net/pages/view/1287"
                },
                "data\\Технология строительных процессов\\Монолитное домостроение\\Опалубка_ Классификация_ области применения и конструкции.json"
            ],
            [
                {
                    "title": "Арматурные работы",
                    "url": "https://perekos.net/pages/view/1288"
                },
                "data\\Технология строительных процессов\\Монолитное домостроение\\Арматурные работы.json"
            ],
            [
                {
                    "title": "Бетонные смеси: приготовление, транспортирование и укладка",
                    "url": "https://perekos.net/pages/view/1289"
                },
                "data\\Технология строительных процессов\\Монолитное домостроение\\Бетонные смеси_ приготовление_ транспортирование и укладка.json"
            ],
            [
                {
                    "title": "Уход за бетоном. Исправление дефектов бетонирования",
                    "url": "https://perekos.net/pages/view/1290"
                },
                "data\\Технология строительных процессов\\Монолитное домостроение\\Уход за бетоном_ Исправление дефектов бетонирования.json"
            ],
            [
                {
                    "title": "Специальные методы бетонирования",
                    "url": "https://perekos.net/pages/view/1291"
                },
                "data\\Технология строительных процессов\\Монолитное домостроение\\Специальные методы бетонирования.json"
            ],
            [
                {
                    "title": "Технология и организация возведения монолитных зданий и сооружений",
                    "url": "https://perekos.net/pages/view/1292"
                },
                "data\\Технология строительных процессов\\Монолитное домостроение\\Технология и организация возведения монолитных зданий и сооружений.json"
            ],
            [
                {
                    "title": "Контроль качества бетонных работ",
                    "url": "https://perekos.net/pages/view/1293"
                },
                "data\\Технология строительных процессов\\Монолитное домостроение\\Контроль качества бетонных работ.json"
            ],
            [
                {
                    "title": "Техника безопасности при производстве бетонных работ",
                    "url": "https://perekos.net/pages/view/1294"
                },
                "data\\Технология строительных процессов\\Монолитное домостроение\\Техника безопасности при производстве бетонных работ.json"
            ],
            [
                {
                    "title": "Изоляция строительных конструкций",
                    "url": "https://perekos.net/sections/view/116"
                },
                "data\\Технология строительных процессов\\Изоляция строительных конструкций\\Изоляция строительных конструкций.json"
            ],
            [
                {
                    "title": "Аккредитация организаций, оказывающих услуги в области охраны труда",
                    "url": "https://perekos.net/pages/view/555"
                },
                "data\\Технология строительных процессов\\Охрана труда в строительстве\\Аккредитация организаций_ оказывающих услуги в области охраны труда.json"
            ],
            [
                {
                    "title": "Реестр аккредитованных организаций, оказывающих услуги в области охраны труда",
                    "url": "https://perekos.net/pages/view/556"
                },
                "data\\Технология строительных процессов\\Охрана труда в строительстве\\Реестр аккредитованных организаций_ оказывающих услуги в области охраны труда.json"
            ],
            [
                {
                    "title": "Алгоритм расследования несчастных случаев на производстве",
                    "url": "https://perekos.net/pages/view/557"
                },
                "data\\Технология строительных процессов\\Охрана труда в строительстве\\Алгоритм расследования несчастных случаев на производстве.json"
            ],
            [
                {
                    "title": "Анализ состояния травматизма на производстве",
                    "url": "https://perekos.net/pages/view/558"
                },
                "data\\Технология строительных процессов\\Охрана труда в строительстве\\Анализ состояния травматизма на производстве.json"
            ],
            [
                {
                    "title": "Проведение проверок государственными органами правопорядка",
                    "url": "https://perekos.net/pages/view/559"
                },
                "data\\Технология строительных процессов\\Охрана труда в строительстве\\Проведение проверок государственными органами правопорядка.json"
            ],
            [
                {
                    "title": "Инструктаж, обучение и проверка знаний работников, специалистов и руководителей организаций по охране труда",
                    "url": "https://perekos.net/pages/view/560"
                },
                "data\\Технология строительных процессов\\Охрана труда в строительстве\\Инструктаж_ обучение и проверка знаний работников_ специалистов и руководителей организаций по охране труда.json"
            ],
            [
                {
                    "title": "Минералы и горные породы",
                    "url": "https://perekos.net/pages/view/563"
                },
                "data\\Технология строительных процессов\\Инженерная геология в строительстве\\Минералы и горные породы.json"
            ],
            [
                {
                    "title": "Инженерно-геологические свойства горных пород",
                    "url": "https://perekos.net/pages/view/564"
                },
                "data\\Технология строительных процессов\\Инженерная геология в строительстве\\Инженерно-геологические свойства горных пород.json"
            ],
            [
                {
                    "title": "Экзогенные и эндогенные геодинамические процессы",
                    "url": "https://perekos.net/pages/view/565"
                },
                "data\\Технология строительных процессов\\Инженерная геология в строительстве\\Экзогенные и эндогенные геодинамические процессы.json"
            ],
            [
                {
                    "title": "Общие вопросы строительного проектирования",
                    "url": "https://perekos.net/sections/view/299"
                },
                "data\\Проектирование строительных конструкций\\Общие вопросы строительного проектирования\\Общие вопросы строительного проектирования.json"
            ],
            [
                {
                    "title": "1. Соотношения единиц физических величин",
                    "url": "https://perekos.net/pages/view/791"
                },
                "data\\Проектирование строительных конструкций\\Расчет строительных конструкций\\1_ Соотношения единиц физических величин.json"
            ],
            [
                {
                    "title": "2. Нагрузки и воздействия",
                    "url": "https://perekos.net/pages/view/792"
                },
                "data\\Проектирование строительных конструкций\\Расчет строительных конструкций\\2_ Нагрузки и воздействия.json"
            ],
            [
                {
                    "title": "3. Группы режимов работы кранов",
                    "url": "https://perekos.net/pages/view/793"
                },
                "data\\Проектирование строительных конструкций\\Расчет строительных конструкций\\3_ Группы режимов работы кранов.json"
            ],
            [
                {
                    "title": "4. Карты районирования территории по климатическим характеристикам",
                    "url": "https://perekos.net/pages/view/794"
                },
                "data\\Проектирование строительных конструкций\\Расчет строительных конструкций\\4_ Карты районирования территории по климатическим характеристикам.json"
            ],
            [
                {
                    "title": "5. Основные формулы сопротивления материалов. Осевое растяжение и сжатие",
                    "url": "https://perekos.net/pages/view/795"
                },
                "data\\Проектирование строительных конструкций\\Расчет строительных конструкций\\5_ Основные формулы сопротивления материалов_ Осевое растяжение и сжатие.json"
            ],
            [
                {
                    "title": "6. Растяжение-сжатие по двум направлениям",
                    "url": "https://perekos.net/pages/view/796"
                },
                "data\\Проектирование строительных конструкций\\Расчет строительных конструкций\\6_ Растяжение-сжатие по двум направлениям.json"
            ],
            [
                {
                    "title": "7. Моменты инерции плоских фигур",
                    "url": "https://perekos.net/pages/view/797"
                },
                "data\\Проектирование строительных конструкций\\Расчет строительных конструкций\\7_ Моменты инерции плоских фигур.json"
            ],
            [
                {
                    "title": "8. Определение напряжений при изгибе прямого бруса",
                    "url": "https://perekos.net/pages/view/798"
                },
                "data\\Проектирование строительных конструкций\\Расчет строительных конструкций\\8_ Определение напряжений при изгибе прямого бруса.json"
            ],
            [
                {
                    "title": "9. Упругая линия бруса",
                    "url": "https://perekos.net/pages/view/799"
                },
                "data\\Проектирование строительных конструкций\\Расчет строительных конструкций\\9_ Упругая линия бруса.json"
            ],
            [
                {
                    "title": "10. Внецентренное сжатие и растяжение. Ядро сечения",
                    "url": "https://perekos.net/pages/view/800"
                },
                "data\\Проектирование строительных конструкций\\Расчет строительных конструкций\\10_ Внецентренное сжатие и растяжение_ Ядро сечения.json"
            ],
            [
                {
                    "title": "11. Косой изгиб и косое внецентренное сжатие (растяжение)",
                    "url": "https://perekos.net/pages/view/801"
                },
                "data\\Проектирование строительных конструкций\\Расчет строительных конструкций\\11_ Косой изгиб и косое внецентренное сжатие _растяжение_.json"
            ],
            [
                {
                    "title": "12. Продольный изгиб",
                    "url": "https://perekos.net/pages/view/802"
                },
                "data\\Проектирование строительных конструкций\\Расчет строительных конструкций\\12_ Продольный изгиб.json"
            ],
            [
                {
                    "title": "13. Балка на упругом основании",
                    "url": "https://perekos.net/pages/view/803"
                },
                "data\\Проектирование строительных конструкций\\Расчет строительных конструкций\\13_ Балка на упругом основании.json"
            ],
            [
                {
                    "title": "Определение внутренних усилий строительных конструкций",
                    "url": "https://perekos.net/sections/view/303"
                },
                "data\\Проектирование строительных конструкций\\Определение внутренних усилий строительных конструкций\\Определение внутренних усилий строительных конструкций.json"
            ],
            [
                {
                    "title": "Проектирование оснований и фундаментов",
                    "url": "https://perekos.net/sections/view/304"
                },
                "data\\Проектирование строительных конструкций\\Проектирование оснований и фундаментов\\Проектирование оснований и фундаментов.json"
            ],
            [
                {
                    "title": "Проектирование бетонных и железобетонных конструкций",
                    "url": "https://perekos.net/sections/view/305"
                },
                "data\\Проектирование строительных конструкций\\Проектирование бетонных и железобетонных конструкций\\Проектирование бетонных и железобетонных конструкций.json"
            ],
            [
                {
                    "title": "Проектирование металлических конструкций",
                    "url": "https://perekos.net/sections/view/306"
                },
                "data\\Проектирование строительных конструкций\\Проектирование металлических конструкций\\Проектирование металлических конструкций.json"
            ],
            [
                {
                    "title": "Проектирование деревянных конструкций",
                    "url": "https://perekos.net/sections/view/307"
                },
                "data\\Проектирование строительных конструкций\\Проектирование деревянных конструкций\\Проектирование деревянных конструкций.json"
            ],
            [
                {
                    "title": "Проектирование пластиковых конструкций",
                    "url": "https://perekos.net/sections/view/308"
                },
                "data\\Проектирование строительных конструкций\\Проектирование пластиковых конструкций\\Проектирование пластиковых конструкций.json"
            ],
            [
                {
                    "title": "Теплотехнический расчет ограждающих конструкций",
                    "url": "https://perekos.net/sections/view/310"
                },
                "data\\Проектирование строительных конструкций\\Теплотехнический расчет ограждающих конструкций\\Теплотехнический расчет ограждающих конструкций.json"
            ],
            [
                {
                    "title": "Акустический расчет ограждающих конструкций",
                    "url": "https://perekos.net/sections/view/311"
                },
                "data\\Проектирование строительных конструкций\\Акустический расчет ограждающих конструкций\\Акустический расчет ограждающих конструкций.json"
            ],
            [
                {
                    "title": "Проектирование инженерных систем",
                    "url": "https://perekos.net/sections/view/312"
                },
                "data\\Проектирование строительных конструкций\\Проектирование инженерных систем\\Проектирование инженерных систем.json"
            ],
            [
                {
                    "title": "Проектирование каменных и армокаменных конструкций",
                    "url": "https://perekos.net/sections/view/336"
                },
                "data\\Проектирование строительных конструкций\\Проектирование каменных и армокаменных конструкций\\Проектирование каменных и армокаменных конструкций.json"
            ],
            [
                {
                    "title": "Принципы теплозащиты зданий",
                    "url": "https://perekos.net/pages/view/1478"
                },
                "data\\Проектирование строительных конструкций\\Тепловая защита зданий\\Принципы теплозащиты зданий.json"
            ],
            [
                {
                    "title": "Сопротивление теплопередаче элементов ограждающих конструкций",
                    "url": "https://perekos.net/pages/view/1479"
                },
                "data\\Проектирование строительных конструкций\\Тепловая защита зданий\\Сопротивление теплопередаче элементов ограждающих конструкций.json"
            ],
            [
                {
                    "title": "Проектирование и технологии тепловой защиты зданий",
                    "url": "https://perekos.net/pages/view/1480"
                },
                "data\\Проектирование строительных конструкций\\Тепловая защита зданий\\Проектирование и технологии тепловой защиты зданий.json"
            ],
            [
                {
                    "title": "Акустические материалы",
                    "url": "https://perekos.net/sections/view/60"
                },
                "data\\Строительные материалы\\Акустические материалы\\Акустические материалы.json"
            ],
            [
                {
                    "title": "Бетоны",
                    "url": "https://perekos.net/sections/view/53"
                },
                "data\\Строительные материалы\\Бетоны\\Бетоны.json"
            ],
            [
                {
                    "title": "Изоляционные материалы",
                    "url": "https://perekos.net/sections/view/50"
                },
                "data\\Строительные материалы\\Изоляционные материалы\\Изоляционные материалы.json"
            ],
            [
                {
                    "title": "Керамические материалы",
                    "url": "https://perekos.net/sections/view/55"
                },
                "data\\Строительные материалы\\Керамические материалы\\Керамические материалы.json"
            ],
            [
                {
                    "title": "Лесные материалы",
                    "url": "https://perekos.net/sections/view/57"
                },
                "data\\Строительные материалы\\Лесные материалы\\Лесные материалы.json"
            ],
            [
                {
                    "title": "Металлические материалы",
                    "url": "https://perekos.net/sections/view/54"
                },
                "data\\Строительные материалы\\Металлические материалы\\Металлические материалы.json"
            ],
            [
                {
                    "title": "Отделочные материалы",
                    "url": "https://perekos.net/sections/view/51"
                },
                "data\\Строительные материалы\\Отделочные материалы\\Отделочные материалы.json"
            ],
            [
                {
                    "title": "Полимерные материалы в строительстве",
                    "url": "https://perekos.net/sections/view/59"
                },
                "data\\Строительные материалы\\Полимерные материалы в строительстве\\Полимерные материалы в строительстве.json"
            ],
            [
                {
                    "title": "Природные каменные материалы в строительстве",
                    "url": "https://perekos.net/sections/view/61"
                },
                "data\\Строительные материалы\\Природные каменные материалы в строительстве\\Природные каменные материалы в строительстве.json"
            ],
            [
                {
                    "title": "Стекло в строительстве",
                    "url": "https://perekos.net/sections/view/52"
                },
                "data\\Строительные материалы\\Стекло в строительстве\\Стекло в строительстве.json"
            ],
            [
                {
                    "title": "Строительные растворы",
                    "url": "https://perekos.net/sections/view/56"
                },
                "data\\Строительные материалы\\Строительные растворы\\Строительные растворы.json"
            ],
            [
                {
                    "title": "Теплоизоляционные материалы в строительстве",
                    "url": "https://perekos.net/sections/view/58"
                },
                "data\\Строительные материалы\\Теплоизоляционные материалы в строительстве\\Теплоизоляционные материалы в строительстве.json"
            ],
            [
                {
                    "title": "Классификация промышленных зданий",
                    "url": "https://perekos.net/pages/view/1303"
                },
                "data\\Архитектура гражданских и промышленных зданий\\Архитектура промышленных зданий\\Классификация промышленных зданий.json"
            ],
            [
                {
                    "title": "Типизация и унификация промышленных зданий",
                    "url": "https://perekos.net/pages/view/1304"
                },
                "data\\Архитектура гражданских и промышленных зданий\\Архитектура промышленных зданий\\Типизация и унификация промышленных зданий.json"
            ],
            [
                {
                    "title": "Привязка конструктивных элементов зданий к разбивочным осям",
                    "url": "https://perekos.net/pages/view/1305"
                },
                "data\\Архитектура гражданских и промышленных зданий\\Архитектура промышленных зданий\\Привязка конструктивных элементов зданий к разбивочным осям.json"
            ],
            [
                {
                    "title": "Объемно-планировочные решения промышленных зданий",
                    "url": "https://perekos.net/pages/view/1306"
                },
                "data\\Архитектура гражданских и промышленных зданий\\Архитектура промышленных зданий\\Объемно-планировочные решения промышленных зданий.json"
            ],
            [
                {
                    "title": "Конструктивные решения промышленных зданий",
                    "url": "https://perekos.net/pages/view/1312"
                },
                "data\\Архитектура гражданских и промышленных зданий\\Архитектура промышленных зданий\\Конструктивные решения промышленных зданий.json"
            ],
            [
                {
                    "title": "Фундаменты промышленных зданий",
                    "url": "https://perekos.net/pages/view/1313"
                },
                "data\\Архитектура гражданских и промышленных зданий\\Архитектура промышленных зданий\\Фундаменты промышленных зданий.json"
            ],
            [
                {
                    "title": "Железобетонные колонны в промышленных зданиях",
                    "url": "https://perekos.net/pages/view/1314"
                },
                "data\\Архитектура гражданских и промышленных зданий\\Архитектура промышленных зданий\\Железобетонные колонны в промышленных зданиях.json"
            ],
            [
                {
                    "title": "Стальные колонны в промышленных зданиях",
                    "url": "https://perekos.net/pages/view/1315"
                },
                "data\\Архитектура гражданских и промышленных зданий\\Архитектура промышленных зданий\\Стальные колонны в промышленных зданиях.json"
            ],
            [
                {
                    "title": "Колонны фахверков",
                    "url": "https://perekos.net/pages/view/1316"
                },
                "data\\Архитектура гражданских и промышленных зданий\\Архитектура промышленных зданий\\Колонны фахверков.json"
            ],
            [
                {
                    "title": "Связи по колоннам в промышленных зданиях",
                    "url": "https://perekos.net/pages/view/1317"
                },
                "data\\Архитектура гражданских и промышленных зданий\\Архитектура промышленных зданий\\Связи по колоннам в промышленных зданиях.json"
            ],
            [
                {
                    "title": "Подкрановые балки в промышленных зданиях",
                    "url": "https://perekos.net/pages/view/1318"
                },
                "data\\Архитектура гражданских и промышленных зданий\\Архитектура промышленных зданий\\Подкрановые балки в промышленных зданиях.json"
            ],
            [
                {
                    "title": "Несущие конструкции покрытия в промышленных зданиях",
                    "url": "https://perekos.net/pages/view/1319"
                },
                "data\\Архитектура гражданских и промышленных зданий\\Архитектура промышленных зданий\\Несущие конструкции покрытия в промышленных зданиях.json"
            ],
            [
                {
                    "title": "Связи в покрытиях промышленных зданиях",
                    "url": "https://perekos.net/pages/view/1320"
                },
                "data\\Архитектура гражданских и промышленных зданий\\Архитектура промышленных зданий\\Связи в покрытиях промышленных зданиях.json"
            ],
            [
                {
                    "title": "Фонари промышленных зданий",
                    "url": "https://perekos.net/pages/view/1321"
                },
                "data\\Архитектура гражданских и промышленных зданий\\Архитектура промышленных зданий\\Фонари промышленных зданий.json"
            ],
            [
                {
                    "title": "Ограждающие конструкции покрытий промышленных зданий",
                    "url": "https://perekos.net/pages/view/1325"
                },
                "data\\Архитектура гражданских и промышленных зданий\\Архитектура промышленных зданий\\Ограждающие конструкции покрытий промышленных зданий.json"
            ],
            [
                {
                    "title": "Стены промышленных зданий",
                    "url": "https://perekos.net/pages/view/1326"
                },
                "data\\Архитектура гражданских и промышленных зданий\\Архитектура промышленных зданий\\Стены промышленных зданий.json"
            ],
            [
                {
                    "title": "Планировка промышленного здания",
                    "url": "https://perekos.net/pages/view/1327"
                },
                "data\\Архитектура гражданских и промышленных зданий\\Архитектура промышленных зданий\\Планировка промышленного здания.json"
            ],
            [
                {
                    "title": "Гражданские здания_ Понятие о зданиях и их классификация",
                    "url": "https://perekos.net/sections/view/419"
                },
                "data\\Архитектура гражданских и промышленных зданий\\Гражданские здания_ Понятие о зданиях и их классификация\\Гражданские здания_ Понятие о зданиях и их классификация.json"
            ],
            [
                {
                    "title": "Фундаменты",
                    "url": "https://perekos.net/sections/view/418"
                },
                "data\\Архитектура гражданских и промышленных зданий\\Фундаменты\\Фундаменты.json"
            ],
            [
                {
                    "title": "Основание под фундамент",
                    "url": "https://perekos.net/sections/view/420"
                },
                "data\\Архитектура гражданских и промышленных зданий\\Основание под фундамент\\Основание под фундамент.json"
            ],
            [
                {
                    "title": "Стены",
                    "url": "https://perekos.net/sections/view/421"
                },
                "data\\Архитектура гражданских и промышленных зданий\\Стены\\Стены.json"
            ],
            [
                {
                    "title": "Перекрытия",
                    "url": "https://perekos.net/sections/view/422"
                },
                "data\\Архитектура гражданских и промышленных зданий\\Перекрытия\\Перекрытия.json"
            ],
            [
                {
                    "title": "Полы",
                    "url": "https://perekos.net/sections/view/423"
                },
                "data\\Архитектура гражданских и промышленных зданий\\Полы\\Полы.json"
            ],
            [
                {
                    "title": "Крыши",
                    "url": "https://perekos.net/sections/view/424"
                },
                "data\\Архитектура гражданских и промышленных зданий\\Крыши\\Крыши.json"
            ],
            [
                {
                    "title": "Перегородки",
                    "url": "https://perekos.net/sections/view/425"
                },
                "data\\Архитектура гражданских и промышленных зданий\\Перегородки\\Перегородки.json"
            ],
            [
                {
                    "title": "Двери и окна",
                    "url": "https://perekos.net/sections/view/426"
                },
                "data\\Архитектура гражданских и промышленных зданий\\Двери и окна\\Двери и окна.json"
            ],
            [
                {
                    "title": "Лестницы",
                    "url": "https://perekos.net/sections/view/427"
                },
                "data\\Архитектура гражданских и промышленных зданий\\Лестницы\\Лестницы.json"
            ],
            [
                {
                    "title": "Крупноблочные здания",
                    "url": "https://perekos.net/sections/view/413"
                },
                "data\\Архитектура гражданских и промышленных зданий\\Крупноблочные здания\\Крупноблочные здания.json"
            ],
            [
                {
                    "title": "Крупнопанельные здания",
                    "url": "https://perekos.net/sections/view/414"
                },
                "data\\Архитектура гражданских и промышленных зданий\\Крупнопанельные здания\\Крупнопанельные здания.json"
            ],
            [
                {
                    "title": "Здания из сборных блоков",
                    "url": "https://perekos.net/sections/view/415"
                },
                "data\\Архитектура гражданских и промышленных зданий\\Здания из сборных блоков\\Здания из сборных блоков.json"
            ],
            [
                {
                    "title": "Конструкции зданий монолитной и сборно-монолитной строительных систем",
                    "url": "https://perekos.net/sections/view/416"
                },
                "data\\Архитектура гражданских и промышленных зданий\\Конструкции зданий монолитной и сборно-монолитной строительных систем\\Конструкции зданий монолитной и сборно-монолитной строительных систем.json"
            ],
            [
                {
                    "title": "Большепролетные покрытия",
                    "url": "https://perekos.net/sections/view/417"
                },
                "data\\Архитектура гражданских и промышленных зданий\\Большепролетные покрытия\\Большепролетные покрытия.json"
            ]
        ]
    },
    "pages_content_container_selector": "page_text",
    "parsed_data_dir": "data",
    "sitemap": {
        "categories": [
            {
                "articles": [],
                "name": "Технология строительных процессов",
                "subcategories": [
                    {
                        "articles": [],
                        "name": "Бетонные и железобетонные работы",
                        "subcategories": [],
                        "url": "https://perekos.net/sections/view/68"
                    },
                    {
                        "articles": [],
                        "name": "Буровзрывные и свайные работы",
                        "subcategories": [],
                        "url": "https://perekos.net/sections/view/65"
                    },
                    {
                        "articles": [],
                        "name": "Каменные работы в строительстве",
                        "subcategories": [],
                        "url": "https://perekos.net/sections/view/109"
                    },
                    {
                        "articles": [],
                        "name": "Монтаж деревянных конструкций",
                        "subcategories": [],
                        "url": "https://perekos.net/sections/view/105"
                    },
                    {
                        "articles": [],
                        "name": "Монтажные работы в строительстве",
                        "subcategories": [],
                        "url": "https://perekos.net/sections/view/67"
                    },
                    {
                        "articles": [],
                        "name": "Отделочные работы",
                        "subcategories": [],
                        "url": "https://perekos.net/sections/view/66"
                    },
                    {
                        "articles": [],
                        "name": "Реконструкция зданий и сооружений",
                        "subcategories": [],
                        "url": "https://perekos.net/sections/view/63"
                    },
                    {
                        "articles": [],
                        "name": "Теплогазоснабжение, вентиляция и водоотведение",
                        "subcategories": [
                            {
                                "articles": [],
                                "name": "Водоснабжение и водоотведение в строительстве",
                                "subcategories": [],
                                "url": "https://perekos.net/sections/view/240"
                            },
                            {
                                "articles": [],
                                "name": "Теплогазоснабжение и вентиляция в строительстве",
                                "subcategories": [],
                                "url": "https://perekos.net/sections/view/241"
                            }
                        ],
                        "url": "https://perekos.net/sections/view/159"
                    },
                    {
                        "articles": [],
                        "name": "Земляные работы в строительстве",
                        "subcategories": [],
                        "url": "https://perekos.net/sections/view/69"
                    },
                    {
                        "articles": [],
                        "name": "Кровельные работы",
                        "subcategories": [],
                        "url": "https://perekos.net/sections/view/64"
                    },
                    {
                        "articles": [
                            {
                                "title": "История развития монолитного строительства",
                                "url": "https://perekos.net/pages/view/1285"
                            },
                            {
                                "title": "Конструктивные системы и конструкции монолитных зданий",
                                "url": "https://perekos.net/pages/view/1286"
                            },
                            {
                                "title": "Опалубка. Классификация, области применения и конструкции",
                                "url": "https://perekos.net/pages/view/1287"
                            },
                            {
                                "title": "Арматурные работы",
                                "url": "https://perekos.net/pages/view/1288"
                            },
                            {
                                "title": "Бетонные смеси: приготовление, транспортирование и укладка",
                                "url": "https://perekos.net/pages/view/1289"
                            },
                            {
                                "title": "Уход за бетоном. Исправление дефектов бетонирования",
                                "url": "https://perekos.net/pages/view/1290"
                            },
                            {
                                "title": "Специальные методы бетонирования",
                                "url": "https://perekos.net/pages/view/1291"
                            },
                            {
                                "title": "Технология и организация возведения монолитных зданий и сооружений",
                                "url": "https://perekos.net/pages/view/1292"
                            },
                            {
                                "title": "Контроль качества бетонных работ",
                                "url": "https://perekos.net/pages/view/1293"
                            },
                            {
                                "title": "Техника безопасности при производстве бетонных работ",
                                "url": "https://perekos.net/pages/view/1294"
                            }
                        ],
                        "name": "Монолитное домостроение",
                        "subcategories": [],
                        "url": "https://perekos.net/sections/view/441"
                    },
                    {
                        "articles": [],
                        "name": "Изоляция строительных конструкций",
                        "subcategories": [],
                        "url": "https://perekos.net/sections/view/116"
                    },
                    {
                        "articles": [
                            {
                                "title": "Аккредитация организаций, оказывающих услуги в области охраны труда",
                                "url": "https://perekos.net/pages/view/555"
                            },
                            {
                                "title": "Реестр аккредитованных организаций, оказывающих услуги в области охраны труда",
                                "url": "https://perekos.net/pages/view/556"
                            },
                            {
                                "title": "Алгоритм расследования несчастных случаев на производстве",
                                "url": "https://perekos.net/pages/view/557"
                            },
                            {
                                "title": "Анализ состояния травматизма на производстве",
                                "url": "https://perekos.net/pages/view/558"
                            },
                            {
                                "title": "Проведение проверок государственными органами правопорядка",
                                "url": "https://perekos.net/pages/view/559"
                            },
                            {
                                "title": "Инструктаж, обучение и проверка знаний работников, специалистов и руководителей организаций по охране труда",
                                "url": "https://perekos.net/pages/view/560"
                            }
                        ],
                        "name": "Охрана труда в строительстве",
                        "subcategories": [],
                        "url": "https://perekos.net/sections/view/148"
                    },
                    {
                        "articles": [
                            {
                                "title": "Минералы и горные породы",
                                "url": "https://perekos.net/pages/view/563"
                            },
                            {
                                "title": "Инженерно-геологические свойства горных пород",
                                "url": "https://perekos.net/pages/view/564"
                            },
                            {
                                "title": "Экзогенные и эндогенные геодинамические процессы",
                                "url": "https://perekos.net/pages/view/565"
                            }
                        ],
                        "name": "Инженерная геология в строительстве",
                        "subcategories": [],
                        "url": "https://perekos.net/sections/view/275"
                    }
                ],
                "url": "https://perekos.net/sections/view/62"
            },
            {
                "articles": [],
                "name": "Проектирование строительных конструкций",
                "subcategories": [
                    {
                        "articles": [],
                        "name": "Общие вопросы строительного проектирования",
                        "subcategories": [],
                        "url": "https://perekos.net/sections/view/299"
                    },
                    {
                        "articles": [
                            {
                                "title": "1. Соотношения единиц физических величин",
                                "url": "https://perekos.net/pages/view/791"
                            },
                            {
                                "title": "2. Нагрузки и воздействия",
                                "url": "https://perekos.net/pages/view/792"
                            },
                            {
                                "title": "3. Группы режимов работы кранов",
                                "url": "https://perekos.net/pages/view/793"
                            },
                            {
                                "title": "4. Карты районирования территории по климатическим характеристикам",
                                "url": "https://perekos.net/pages/view/794"
                            },
                            {
                                "title": "5. Основные формулы сопротивления материалов. Осевое растяжение и сжатие",
                                "url": "https://perekos.net/pages/view/795"
                            },
                            {
                                "title": "6. Растяжение-сжатие по двум направлениям",
                                "url": "https://perekos.net/pages/view/796"
                            },
                            {
                                "title": "7. Моменты инерции плоских фигур",
                                "url": "https://perekos.net/pages/view/797"
                            },
                            {
                                "title": "8. Определение напряжений при изгибе прямого бруса",
                                "url": "https://perekos.net/pages/view/798"
                            },
                            {
                                "title": "9. Упругая линия бруса",
                                "url": "https://perekos.net/pages/view/799"
                            },
                            {
                                "title": "10. Внецентренное сжатие и растяжение. Ядро сечения",
                                "url": "https://perekos.net/pages/view/800"
                            },
                            {
                                "title": "11. Косой изгиб и косое внецентренное сжатие (растяжение)",
                                "url": "https://perekos.net/pages/view/801"
                            },
                            {
                                "title": "12. Продольный изгиб",
                                "url": "https://perekos.net/pages/view/802"
                            },
                            {
                                "title": "13. Балка на упругом основании",
                                "url": "https://perekos.net/pages/view/803"
                            }
                        ],
                        "name": "Расчет строительных конструкций",
                        "subcategories": [],
                        "url": "https://perekos.net/sections/view/298"
                    },
                    {
                        "articles": [],
                        "name": "Определение внутренних усилий строительных конструкций",
                        "subcategories": [],
                        "url": "https://perekos.net/sections/view/303"
                    },
                    {
                        "articles": [],
                        "name": "Проектирование оснований и фундаментов",
                        "subcategories": [],
                        "url": "https://perekos.net/sections/view/304"
                    },
                    {
                        "articles": [],
                        "name": "Проектирование бетонных и железобетонных конструкций",
                        "subcategories": [],
                        "url": "https://perekos.net/sections/view/305"
                    },
                    {
                        "articles": [],
                        "name": "Проектирование металлических конструкций",
                        "subcategories": [],
                        "url": "https://perekos.net/sections/view/306"
                    },
                    {
                        "articles": [],
                        "name": "Проектирование деревянных конструкций",
                        "subcategories": [],
                        "url": "https://perekos.net/sections/view/307"
                    },
                    {
                        "articles": [],
                        "name": "Проектирование пластиковых конструкций",
                        "subcategories": [],
                        "url": "https://perekos.net/sections/view/308"
                    },
                    {
                        "articles": [],
                        "name": "Теплотехнический расчет ограждающих конструкций",
                        "subcategories": [],
                        "url": "https://perekos.net/sections/view/310"
                    },
                    {
                        "articles": [],
                        "name": "Акустический расчет ограждающих конструкций",
                        "subcategories": [],
                        "url": "https://perekos.net/sections/view/311"
                    },
                    {
                        "articles": [],
                        "name": "Проектирование инженерных систем",
                        "subcategories": [],
                        "url": "https://perekos.net/sections/view/312"
                    },
                    {
                        "articles": [],
                        "name": "Проектирование каменных и армокаменных конструкций",
                        "subcategories": [],
                        "url": "https://perekos.net/sections/view/336"
                    },
                    {
                        "articles": [
                            {
                                "title": "Принципы теплозащиты зданий",
                                "url": "https://perekos.net/pages/view/1478"
                            },
                            {
                                "title": "Сопротивление теплопередаче элементов ограждающих конструкций",
                                "url": "https://perekos.net/pages/view/1479"
                            },
                            {
                                "title": "Проектирование и технологии тепловой защиты зданий",
                                "url": "https://perekos.net/pages/view/1480"
                            }
                        ],
                        "name": "Тепловая защита зданий",
                        "subcategories": [],
                        "url": "https://perekos.net/sections/view/460"
                    }
                ],
                "url": "https://perekos.net/sections/view/138"
            },
            {
                "articles": [],
                "name": "Строительные материалы",
                "subcategories": [
                    {
                        "articles": [],
                        "name": "Акустические материалы",
                        "subcategories": [],
                        "url": "https://perekos.net/sections/view/60"
                    },
                    {
                        "articles": [],
                        "name": "Бетоны",
                        "subcategories": [],
                        "url": "https://perekos.net/sections/view/53"
                    },
                    {
                        "articles": [],
                        "name": "Изоляционные материалы",
                        "subcategories": [],
                        "url": "https://perekos.net/sections/view/50"
                    },
                    {
                        "articles": [],
                        "name": "Керамические материалы",
                        "subcategories": [],
                        "url": "https://perekos.net/sections/view/55"
                    },
                    {
                        "articles": [],
                        "name": "Лесные материалы",
                        "subcategories": [],
                        "url": "https://perekos.net/sections/view/57"
                    },
                    {
                        "articles": [],
                        "name": "Металлические материалы",
                        "subcategories": [],
                        "url": "https://perekos.net/sections/view/54"
                    },
                    {
                        "articles": [],
                        "name": "Отделочные материалы",
                        "subcategories": [],
                        "url": "https://perekos.net/sections/view/51"
                    },
                    {
                        "articles": [],
                        "name": "Полимерные материалы в строительстве",
                        "subcategories": [],
                        "url": "https://perekos.net/sections/view/59"
                    },
                    {
                        "articles": [],
                        "name": "Природные каменные материалы в строительстве",
                        "subcategories": [],
                        "url": "https://perekos.net/sections/view/61"
                    },
                    {
                        "articles": [],
                        "name": "Стекло в строительстве",
                        "subcategories": [],
                        "url": "https://perekos.net/sections/view/52"
                    },
                    {
                        "articles": [],
                        "name": "Строительные растворы",
                        "subcategories": [],
                        "url": "https://perekos.net/sections/view/56"
                    },
                    {
                        "articles": [],
                        "name": "Теплоизоляционные материалы в строительстве",
                        "subcategories": [],
                        "url": "https://perekos.net/sections/view/58"
                    }
                ],
                "url": "https://perekos.net/sections/view/4"
            },
            {
                "articles": [],
                "name": "Архитектура гражданских и промышленных зданий",
                "subcategories": [
                    {
                        "articles": [
                            {
                                "title": "Классификация промышленных зданий",
                                "url": "https://perekos.net/pages/view/1303"
                            },
                            {
                                "title": "Типизация и унификация промышленных зданий",
                                "url": "https://perekos.net/pages/view/1304"
                            },
                            {
                                "title": "Привязка конструктивных элементов зданий к разбивочным осям",
                                "url": "https://perekos.net/pages/view/1305"
                            },
                            {
                                "title": "Объемно-планировочные решения промышленных зданий",
                                "url": "https://perekos.net/pages/view/1306"
                            },
                            {
                                "title": "Конструктивные решения промышленных зданий",
                                "url": "https://perekos.net/pages/view/1312"
                            },
                            {
                                "title": "Фундаменты промышленных зданий",
                                "url": "https://perekos.net/pages/view/1313"
                            },
                            {
                                "title": "Железобетонные колонны в промышленных зданиях",
                                "url": "https://perekos.net/pages/view/1314"
                            },
                            {
                                "title": "Стальные колонны в промышленных зданиях",
                                "url": "https://perekos.net/pages/view/1315"
                            },
                            {
                                "title": "Колонны фахверков",
                                "url": "https://perekos.net/pages/view/1316"
                            },
                            {
                                "title": "Связи по колоннам в промышленных зданиях",
                                "url": "https://perekos.net/pages/view/1317"
                            },
                            {
                                "title": "Подкрановые балки в промышленных зданиях",
                                "url": "https://perekos.net/pages/view/1318"
                            },
                            {
                                "title": "Несущие конструкции покрытия в промышленных зданиях",
                                "url": "https://perekos.net/pages/view/1319"
                            },
                            {
                                "title": "Связи в покрытиях промышленных зданиях",
                                "url": "https://perekos.net/pages/view/1320"
                            },
                            {
                                "title": "Фонари промышленных зданий",
                                "url": "https://perekos.net/pages/view/1321"
                            },
                            {
                                "title": "Ограждающие конструкции покрытий промышленных зданий",
                                "url": "https://perekos.net/pages/view/1325"
                            },
                            {
                                "title": "Стены промышленных зданий",
                                "url": "https://perekos.net/pages/view/1326"
                            },
                            {
                                "title": "Планировка промышленного здания",
                                "url": "https://perekos.net/pages/view/1327"
                            }
                        ],
                        "name": "Архитектура промышленных зданий",
                        "subcategories": [],
                        "url": "https://perekos.net/sections/view/440"
                    },
                    {
                        "articles": [],
                        "name": "Гражданские здания. Понятие о зданиях и их классификация",
                        "subcategories": [],
                        "url": "https://perekos.net/sections/view/419"
                    },
                    {
                        "articles": [],
                        "name": "Фундаменты",
                        "subcategories": [],
                        "url": "https://perekos.net/sections/view/418"
                    },
                    {
                        "articles": [],
                        "name": "Основание под фундамент",
                        "subcategories": [],
                        "url": "https://perekos.net/sections/view/420"
                    },
                    {
                        "articles": [],
                        "name": "Стены",
                        "subcategories": [],
                        "url": "https://perekos.net/sections/view/421"
                    },
                    {
                        "articles": [],
                        "name": "Перекрытия",
                        "subcategories": [],
                        "url": "https://perekos.net/sections/view/422"
                    },
                    {
                        "articles": [],
                        "name": "Полы",
                        "subcategories": [],
                        "url": "https://perekos.net/sections/view/423"
                    },
                    {
                        "articles": [],
                        "name": "Крыши",
                        "subcategories": [],
                        "url": "https://perekos.net/sections/view/424"
                    },
                    {
                        "articles": [],
                        "name": "Перегородки",
                        "subcategories": [],
                        "url": "https://perekos.net/sections/view/425"
                    },
                    {
                        "articles": [],
                        "name": "Двери и окна",
                        "subcategories": [],
                        "url": "https://perekos.net/sections/view/426"
                    },
                    {
                        "articles": [],
                        "name": "Лестницы",
                        "subcategories": [],
                        "url": "https://perekos.net/sections/view/427"
                    },
                    {
                        "articles": [],
                        "name": "Крупноблочные здания",
                        "subcategories": [],
                        "url": "https://perekos.net/sections/view/413"
                    },
                    {
                        "articles": [],
                        "name": "Крупнопанельные здания",
                        "subcategories": [],
                        "url": "https://perekos.net/sections/view/414"
                    },
                    {
                        "articles": [],
                        "name": "Здания из сборных блоков",
                        "subcategories": [],
                        "url": "https://perekos.net/sections/view/415"
                    },
                    {
                        "articles": [],
                        "name": "Конструкции зданий монолитной и сборно-монолитной строительных систем",
                        "subcategories": [],
                        "url": "https://perekos.net/sections/view/416"
                    },
                    {
                        "articles": [],
                        "name": "Большепролетные покрытия",
                        "subcategories": [],
                        "url": "https://perekos.net/sections/view/417"
                    }
                ],
                "url": "https://perekos.net/sections/view/6"
            }
        ],
        "root_url": "https://perekos.net"
    }
}