{"elements":[{"type":"link","content":"Общие сведения","attributes":{"href":"#position1"}},{"type":"link","content":"Обмазочная и окрасочная гидроизоляция","attributes":{"href":"#position2"}},{"type":"link","content":"Оклеечная гидроизоляция","attributes":{"href":"#position3"}},{"type":"link","content":"Проникающая  гидроизоляция","attributes":{"href":"#position4"}},{"type":"link","content":"Литая асфальтовая изоляция и штукатурка","attributes":{"href":"#position5"}},{"type":"link","content":"Жесткая гидроизоляция","attributes":{"href":"#position6"}},{"type":"link","content":"Антикоррозийная защита","attributes":{"href":"#position7"}},{"type":"link","content":"Тепло- и звукоизоляция конструкций","attributes":{"href":"#position8"}},{"type":"link","content":"Обеспечение звукоизоляции конструкций","attributes":{"href":"#position9"}},{"type":"link","content":"Производство изоляционных работ в зимних условиях","attributes":{"href":"#position10"}},{"type":"link","content":"Техника безопасности при изоляционных работах","attributes":{"href":"#position11"}},{"type":"paragraph","content":"","attributes":{}},{"type":"image","content":"","attributes":{"src":"/default/fast_download/page_images.image_big.8d3234544b76f1ef.696d6167653030342e6a7067.jpg"}},{"type":"paragraph","content":"","attributes":{}},{"type":"paragraph","content":"","attributes":{}},{"type":"subtitle","content":"1. Общие сведения","attributes":{}},{"type":"link","content":"Общие сведения","attributes":{"href":"#position1"}},{"type":"subtitle","content":"2. Обмазочная и окрасочная гидроизоляция","attributes":{}},{"type":"link","content":"Обмазочная и окрасочная гидроизоляция","attributes":{"href":"#position2"}},{"type":"subtitle","content":"3. Оклеечная гидроизоляция","attributes":{}},{"type":"link","content":"Оклеечная гидроизоляция","attributes":{"href":"#position3"}},{"type":"subtitle","content":"4. Проникающая  гидроизоляция","attributes":{}},{"type":"link","content":"Проникающая  гидроизоляция","attributes":{"href":"#position4"}},{"type":"subtitle","content":"5. Литая асфальтовая изоляция и штукатурка","attributes":{}},{"type":"link","content":"Литая асфальтовая изоляция и штукатурка","attributes":{"href":"#position5"}},{"type":"subtitle","content":"6. Жесткая гидроизоляция","attributes":{}},{"type":"link","content":"Жесткая гидроизоляция","attributes":{"href":"#position6"}},{"type":"subtitle","content":"7. Антикоррозийная защита","attributes":{}},{"type":"link","content":"Антикоррозийная защита","attributes":{"href":"#position7"}},{"type":"subtitle","content":"8. Тепло- и звукоизоляция конструкций","attributes":{}},{"type":"link","content":"Тепло- и звукоизоляция конструкций","attributes":{"href":"#position8"}},{"type":"subtitle","content":"9. Обеспечение звукоизоляции конструкций","attributes":{}},{"type":"link","content":"Обеспечение звукоизоляции конструкций","attributes":{"href":"#position9"}},{"type":"subtitle","content":"10. Производство изоляционных работ в зимних условиях","attributes":{}},{"type":"link","content":"Производство изоляционных работ в зимних условиях","attributes":{"href":"#position10"}},{"type":"subtitle","content":"11. Техника безопасности при изоляционных работах","attributes":{}},{"type":"link","content":"Техника безопасности при изоляционных работах","attributes":{"href":"#position11"}},{"type":"paragraph","content":"Нормативная литература:","attributes":{}},{"type":"link","content":"Нормативная литература","attributes":{"href":"https://perekos.net/sections/view/5"}},{"type":"paragraph","content":"ГОСТ 20022.1.90 Защита древесины;  СТ СЭВ 4867.84 Звукоизоляция ограждающих конструкций;  СП 61.13330.2012 Тепловая изоляция оборудования и трубопроводов;  СП 51.13330.2011 Защита от шума;  СП 41.103.2000 Проектирование тепловой изоляции оборудования и трубопроводов;  СП 28.13330.2012 Защита строительных конструкций от коррозии;  СНиП 41.03.2003 Тепловая изоляция оборудования и трубопроводов;  СНиП 23.02.2003 Теловая защита зданий;  СНиП 23.02.2003 Защита от шума;  СНиП 12.01.2004 Организация строительства;  СНиП 3.04.03.85 Защита строительных конструкций и сооружений от коррозии;  СНиП 3.04.01.87 Изоляционные и оделочные покрытия;  Постановление №80 Безопасность труда в строительстве ч.1;  Постанволение №123 Безопасноть труда в строительстве;  ГОСТ Р 52804 .2007 Защита бетонных и железобетонных конструкций от коррозии;  ГОСТ Р 51943.2002 Экраны акустические для защиты от шума транспорта;  ГОСТ Р 9.316.2006 Покрытия термодиффузионные цинковые;  ГОСТ 31384.2008 Защита бетонных и железобетонных конструкций от коррозии;  ГОСТ 30693.2000 Мастики кровельные и гидроизоляционные;  ГОСТ 30547.97 Материалы рулонные кровельные и гидроизоляционные;  ГОСТ 21.513.83 Антикоррозийная защита конструкций зданий и сооружений;  ГОСТ 12.3.016.87 Работы антикоррозийные;  ГОСТ 9.304.87 Покрытия газотермические;  ВСН 32.81 Инструкция по устройству гидроизоляции конструкций мостов","attributes":{}},{"type":"link","content":"ГОСТ 20022.1.90 Защита древесины;","attributes":{"href":"/default/download/page_files.file.9e8ae3da80f24809.6d4f33686b5948616f4b70455065662e646f63.doc"}},{"type":"link","content":"СТ СЭВ 4867.84 Звукоизоляция ограждающих конструкций;","attributes":{"href":"/default/download/page_files.file.ab2f2842f2820ccf.78414b3736464e65646a4a4f4b325a2e646f63.doc"}},{"type":"link","content":"СП 61.13330.2012 Тепловая изоляция оборудования и трубопроводов;","attributes":{"href":"/default/download/page_files.file.94af2ce668aa175d.6332365270664c695565647476454c2e646f63.doc"}},{"type":"link","content":"СП 51.13330.2011 Защита от шума;","attributes":{"href":"/default/download/page_files.file.a134d2f884dbab68.663156574239356f30303555697a322e646f63.doc"}},{"type":"link","content":"СП 41.103.2000 Проектирование тепловой изоляции оборудования и трубопроводов;","attributes":{"href":"/default/download/page_files.file.824ed76f15338f8c.597849366147376f7952787a4a444b2e646f63.doc"}},{"type":"link","content":"СП 28.13330.2012 Защита строительных конструкций от коррозии;","attributes":{"href":"/default/download/page_files.file.92178d5d3da4a2ee.56427a56653030516970744b5a464e2e646f63.doc"}},{"type":"link","content":"СНиП 41.03.2003 Тепловая изоляция оборудования и трубопроводов;","attributes":{"href":"/default/download/page_files.file.9a026ce95cc7683b.666f7966673055306e4968385a464c2e646f63.doc"}},{"type":"link","content":"СНиП 23.02.2003 Теловая защита зданий;","attributes":{"href":"/default/download/page_files.file.8a2f81426090c9f9.63694a4a5a786a725252576e5138472e646f63.doc"}},{"type":"link","content":"СНиП 23.02.2003 Защита от шума;","attributes":{"href":"/default/download/page_files.file.b78baf78a0baf084.6676656153494f706a4479394f78712e646f63.doc"}},{"type":"link","content":"СНиП 12.01.2004 Организация строительства;","attributes":{"href":"/default/download/page_files.file.ac69d597c4059bf0.7a33617671476e79754f463663317a2e646f63.doc"}},{"type":"link","content":"СНиП 3.04.03.85 Защита строительных конструкций и сооружений от коррозии;","attributes":{"href":"/default/download/page_files.file.9debc4dcba8b44d1.324947346a4e5858496776664830512e646f63.doc"}},{"type":"link","content":"СНиП 3.04.01.87 Изоляционные и оделочные покрытия;","attributes":{"href":"/default/download/page_files.file.b89ca0e1317f8b36.434441665a35386e4f704f6d5958712e646f63.doc"}},{"type":"link","content":"Постановление №80 Безопасность труда в строительстве ч.1;","attributes":{"href":"/default/download/page_files.file.876bcd52fa59f1a0.755857385173506576795a484572672e646f63.doc"}},{"type":"link","content":"Постанволение №123 Безопасноть труда в строительстве;","attributes":{"href":"/default/download/page_files.file.888dfa4be8f49ac2.6c70656e6d43583450533867506f682e646f63.doc"}},{"type":"link","content":"ГОСТ Р 52804 .2007 Защита бетонных и железобетонных конструкций от коррозии;","attributes":{"href":"/default/download/page_files.file.ac6ecb074096eb23.44653867314c6e7230584a307a6d7a2e646f63.doc"}},{"type":"link","content":"ГОСТ Р 51943.2002 Экраны акустические для защиты от шума транспорта;","attributes":{"href":"/default/download/page_files.file.b068f4289ea1e107.4d4f4474734c4f6b6e7734486279742e646f63.doc"}},{"type":"link","content":"ГОСТ Р 9.316.2006 Покрытия термодиффузионные цинковые;","attributes":{"href":"/default/download/page_files.file.ad720d87f15c84b1.666c65426854644b634344354c66732e646f63.doc"}},{"type":"link","content":"ГОСТ 31384.2008 Защита бетонных и железобетонных конструкций от коррозии;","attributes":{"href":"/default/download/page_files.file.8887a87140c8279a.7636465771317a6c746f59536136512e646f63.doc"}},{"type":"link","content":"ГОСТ 30693.2000 Мастики кровельные и гидроизоляционные;","attributes":{"href":"/default/download/page_files.file.b93ecf172d0dcab2.5742627a43557a396437506a6645552e646f63.doc"}},{"type":"link","content":"ГОСТ 30547.97 Материалы рулонные кровельные и гидроизоляционные;","attributes":{"href":"/default/download/page_files.file.96d8e73b96350668.325774537536637837366d776375722e646f63.doc"}},{"type":"link","content":"ГОСТ 21.513.83 Антикоррозийная защита конструкций зданий и сооружений;","attributes":{"href":"/default/download/page_files.file.a6107fabc536e14a.414b5554435577764c62334e3235532e646f63.doc"}},{"type":"link","content":"ГОСТ 12.3.016.87 Работы антикоррозийные;","attributes":{"href":"/default/download/page_files.file.9899370893c17c25.667366645033765137735051594e632e646f63.doc"}},{"type":"link","content":"ГОСТ 9.304.87 Покрытия газотермические;","attributes":{"href":"/default/download/page_files.file.ae59a1d0cccce2bb.683154463234626a514e38443661672e646f63.doc"}},{"type":"link","content":"ВСН 32.81 Инструкция по устройству гидроизоляции конструкций мостов","attributes":{"href":"/default/download/page_files.file.896f7286acf788d2.6471547a563569456e6b4a6d3474452e646f63.doc"}},{"type":"paragraph","content":"Справочная литература:","attributes":{}},{"type":"paragraph","content":"","attributes":{}},{"type":"subtitle","content":"1. Общие сведения","attributes":{}},{"type":"link","content":"","attributes":{"href":null}},{"type":"paragraph","content":"Ограждающие конструкции зданий и сооружений из пористых материалов (бетон, кирпич и др.) при длительном воздействии грунтовых и атмосферных влияний поглощают и удерживают воду в порах. Насыщенные влагой материалы теряют свои эксплуатационные качества – понижается их прочность, долговечность, водонепроницаемость.","attributes":{}},{"type":"paragraph","content":"Металл адсорбирует по своей поверхности влагу, которая под действием кислорода приводит к коррозии, сокращающей срок службы и прочность металлических конструкций. Поэтому все строительные конструкции, и особенно подверженные воздействием влаги, защищают покрытиями из гидроматериалов. Такие покрытия называют гидроизоляцией, а работы по их устройству – гидроизоляционными.","attributes":{}},{"type":"paragraph","content":"","attributes":{}},{"type":"paragraph","content":"Можно уменьшить гидроизоляционные работы путем строительства дренажа, глиняных замков, понижения уровня грунтовых вод, планировки территории, устройства отмосток, упрочнения грунтов цементацией, битумизацией, силикатизацией и др.","attributes":{}},{"type":"image","content":"","attributes":{"src":"/default/fast_download/page_images.image_big.8464d038b9cff86e.312e6a7067.jpg"}},{"type":"paragraph","content":"","attributes":{}},{"type":"paragraph","content":"Гидроизоляция подразделяется на пластическую, жесткую и футеровку.","attributes":{}},{"type":"paragraph","content":"Пластическая - обмазочная, окрасочная, оклеечная, литая, проникающая.","attributes":{}},{"type":"paragraph","content":"Жесткие - цементно-песчаная, асфальтовая, упругие покрытия и штукатурки и листовые покрытия.","attributes":{}},{"type":"paragraph","content":"Футеровка - это облицовка поверхности строительных конструкций кислотостойкими мастичными материалами и штучными изделиями.","attributes":{}},{"type":"paragraph","content":"Перед нанесением гидроизоляции выполняют подготовку поверхностей:Для поверхностей из бетонных конструкций:- очистку поверхности от грязи;","attributes":{}},{"type":"paragraph","content":"- снятие бугров и других неровностей;","attributes":{}},{"type":"paragraph","content":"- срезку выступающих концов арматуры;","attributes":{}},{"type":"paragraph","content":"- заделку углублений и раковин цементным раствором;","attributes":{}},{"type":"paragraph","content":"- просушивание поверхностей;","attributes":{}},{"type":"paragraph","content":"- грунтовку.","attributes":{}},{"type":"paragraph","content":"Для поверхностей из кирпича дополнительно выполняют:","attributes":{}},{"type":"paragraph","content":"- очистку поверхностей пескоструйным аппаратом;","attributes":{}},{"type":"paragraph","content":"- увлажнение поверхностей для удаления мелких пылеватых частиц.","attributes":{}},{"type":"paragraph","content":"Для металлических конструкций выполняют следующие подготовительные процессы:","attributes":{}},{"type":"paragraph","content":"- снятие окалины и ржавчины;","attributes":{}},{"type":"paragraph","content":"- устранение различных масел с помощью щеток, скребков или пескоструйным аппаратом.","attributes":{}},{"type":"paragraph","content":"При подготовке кирпичных и бетонных поверхностей под штукатурную гидроизоляцию для лучшего сцепления производят их насечку.","attributes":{}},{"type":"paragraph","content":"Просушивание осуществляют электровоздуходувками, калориферами, лампами и установками инфракрасного излучения.","attributes":{}},{"type":"paragraph","content":"Перед нанесением битумных и окрасочных составов поверхность  грунтуют составом 1:3 битум - соляркой (иногда за 2 раза).","attributes":{}},{"type":"paragraph","content":"Деревянные конструкции после очистки остругивают, трещины и вмятины зашпаклевывают.","attributes":{}},{"type":"paragraph","content":"Металлические конструкции очищают металлическими щетками.","attributes":{}},{"type":"paragraph","content":"Применяют также химический метод очистки (преобразователь ржавчины).","attributes":{}},{"type":"paragraph","content":"При назначении типа гидроизоляции необходимо учитывать:","attributes":{}},{"type":"paragraph","content":"- требуемую сухость изолируемого помещения;","attributes":{}},{"type":"paragraph","content":"- трещиностойкость изолируемых поверхностей;","attributes":{}},{"type":"paragraph","content":"- величину гидростатического напора воды;","attributes":{}},{"type":"paragraph","content":"- температурные и механические воздействия;","attributes":{}},{"type":"paragraph","content":"- агрессивность внешних вод;","attributes":{}},{"type":"paragraph","content":"- имеющийся выбор гидроизоляционных материалов.","attributes":{}},{"type":"paragraph","content":"","attributes":{}},{"type":"subtitle","content":"2. Обмазочная и окрасочная гидроизоляция","attributes":{}},{"type":"link","content":"","attributes":{"href":null}},{"type":"paragraph","content":"Обмазочная гидроизоляция - это сплошной водонепроницаемый слой или несколько слоев остывшей битумной мастики толщиной 2-4мм, нанесенной на поверхность конструкции, а окрасочная изоляция — более тонкий слой (0,2—0,8 мм).","attributes":{}},{"type":"paragraph","content":"Наносят вручную или механизированным способом.","attributes":{}},{"type":"paragraph","content":"Обмазочную гидроизоляцию применяют главным образом для защиты от капиллярной влаги.","attributes":{}},{"type":"paragraph","content":"Доставляют мастику в бачках или автогудронаторах до 5т.","attributes":{}},{"type":"paragraph","content":"Окрасочные составляющие изготавливают из этинолевого лака, с распушенным асбестом и пигментами красителя и наносят на огрунтованную поверхность тем же лаком в 3слоя.","attributes":{}},{"type":"paragraph","content":"Можно наносить при температуре до – 20°С.","attributes":{}},{"type":"paragraph","content":"","attributes":{}},{"type":"subtitle","content":"3. Оклеечная гидроизоляция","attributes":{}},{"type":"link","content":"","attributes":{"href":null}},{"type":"paragraph","content":"Оклеечная гидроизоляция - сплошной водонепроницаемый ковер из гнилостойких рулонных или гибких листов, материалов, наклеенных в 1- 4 слоя на изолируемые горизонтальные, наклонные, вертикальные поверхности специальными мастиками или клеями:","attributes":{}},{"type":"paragraph","content":"- мастики битумные - для рубероида, бризола и других материалов на основе битума;","attributes":{}},{"type":"paragraph","content":"- специальные клеи и эпоксидные смолыдля полихлорвиниловыхи других пластмассовых ленточных и листовых материалов.","attributes":{}},{"type":"paragraph","content":"Наклеивают на сухую огрунтованную поверхность, на вертикальные поверхности наклейку ведут снизу вверх по 1,2-1,5 м.","attributes":{}},{"type":"paragraph","content":"","attributes":{}},{"type":"paragraph","content":"При высоком уровне грунтовых вод и большом ее давлении оклеечную гидроизоляцию защищают футеровкой из кирпича","attributes":{}},{"type":"image","content":"","attributes":{"src":"/default/fast_download/page_images.image_big.8464d038b9cff86e.312e6a7067.jpg"}},{"type":"paragraph","content":"","attributes":{}},{"type":"paragraph","content":"4. Проникающая  гидроизоляция","attributes":{}},{"type":"link","content":"","attributes":{"href":null}},{"type":"paragraph","content":"Проникающая гидроизоляция предназначена для объемной гидроизоляции водопроницаемого пористого материала. Принцип действия основан на проникновении в пористую структуру приповерхностной зоны изолируемого материала растворов рабочих веществ и их фиксации в толще материала в виде нерастворимых химических соединений, заполняющих поры с вытеснением из них жидкости.","attributes":{}},{"type":"paragraph","content":"Введение в состав приникающей гидроизоляции специальных компонент позволяет проводить дополнительную модификацию свойств обрабатываемого материала:","attributes":{}},{"type":"paragraph","content":"- предотвращение коррозионных процессов в арматурных элементах железобетонного основания;","attributes":{}},{"type":"paragraph","content":"- восстановления технических характеристик \"старого\" бетонного камня;","attributes":{}},{"type":"paragraph","content":"- подавление плесени и грибковых образований;","attributes":{}},{"type":"paragraph","content":"- повышение химической стойкости материала.","attributes":{}},{"type":"paragraph","content":"Применяется в виде суспензий – наносится как окрасочная гидроизоляция, или в виде сухих смесей, которые после затворения наносятся как штукатурка.","attributes":{}},{"type":"paragraph","content":"","attributes":{}},{"type":"subtitle","content":"5. Литая асфальтовая изоляция и штукатурка","attributes":{}},{"type":"link","content":"","attributes":{"href":null}},{"type":"paragraph","content":"Литую гидроизоляцию выполняют путем розлива или залива в полость между изолированной поверхностью здания и защитной стенкой горячего асфальтового раствора или мастики.","attributes":{}},{"type":"paragraph","content":"Наносят слоем 10 – 40 мм.","attributes":{}},{"type":"paragraph","content":"Литую изоляцию часто используют в качестве подстилающего слоя под устройство наливных полов.","attributes":{}},{"type":"paragraph","content":"Литую гидроизоляцию вертикальных поверхностей устраивают путем поярусной, высотой 20 – 40 см, заливки в полость между изолируемой поверхностью и ограждающей стенкой.","attributes":{}},{"type":"paragraph","content":"Литая гидроизоляция не должна иметь трещин, раковин и расслоений.","attributes":{}},{"type":"paragraph","content":"При необходимости горизонтальные и вертикальные гидроизоляционные покрытия защищают слоем раствора.","attributes":{}},{"type":"paragraph","content":"Штукатурная изоляция может быть цементно-песчаная и асфальтовая.","attributes":{}},{"type":"paragraph","content":"Цементно-песчаная представляет собой слой затвердевшего и прочно сцепившегося с изолируемой поверхностью раствора, имеющего повышенную плотность.","attributes":{}},{"type":"paragraph","content":"Надежность изоляции повышается при армировании металлическими сетками или стеклотканевыми материалами.","attributes":{}},{"type":"paragraph","content":"Для растворов применяют водонепроницаемый безусадочный цемент или портландцемент с уплотняющими добавками – церезитом, хлорным железом, жидким стеклом, алюминатом натрия, битумными и латексными эмульсиями.","attributes":{}},{"type":"paragraph","content":"Цементно-песчаную гидроизоляцию наносят растворонасосом слоями по 8 – 10 мм при общем слое 20 – 30 мм. На верхнем накрывочном слое устраивают железнение. Либо выполняют торкретирование.","attributes":{}},{"type":"paragraph","content":"Асфальтовую штукатурную изоляцию применяют для защиты конструкций от капиллярной влаги, а также там, где требуется повышение прочности покрытия.","attributes":{}},{"type":"paragraph","content":"Выполняют в виде сплошного покрытия, образуемого из горячих асфальтовых мастик или растворов либо холодных эмульсионных мастик и паст.","attributes":{}},{"type":"paragraph","content":"Горячие мастики наносят при tо +160°С +180оС. Наносятся асфальтометами под давлением сжатого воздуха 4атм.","attributes":{}},{"type":"paragraph","content":"Холодные мастики наносятся диафрагмовыми насосами.","attributes":{}},{"type":"paragraph","content":"","attributes":{}},{"type":"subtitle","content":"6. Жесткая гидроизоляция","attributes":{}},{"type":"link","content":"","attributes":{"href":null}},{"type":"paragraph","content":"Листовые гидроизоляционные покрытия - это сплошные (сварные) водонепроницаемые ограждения строительных конструкций из стальных или пластмассовых листов.","attributes":{}},{"type":"paragraph","content":"Стальные листы  -  применяют при больших гидротехнических напорах, когда надо обеспечить постоянную сухость помещений в условиях высоких температур и динамических нагрузок, а также в небольших помещениях, имеющих сложную конфигурацию.","attributes":{}},{"type":"paragraph","content":"Например, в насосных станциях, углубленных котельных. Применяют стальные или алюминиевые листы толщиной 2 – 6 мм.","attributes":{}},{"type":"paragraph","content":"Устраивают изоляцию изнутри, иногда снаружи сооружения.","attributes":{}},{"type":"paragraph","content":"Пластмассовые  -  поливинилхлоридные или виниловые покрытия.","attributes":{}},{"type":"paragraph","content":"Применяют главным образом для защиты конструкций от агрессивных сред (резервуары и др.)","attributes":{}},{"type":"paragraph","content":"Гидроизоляцию из пластмассовых листов выполняют сваркой листов,  выкроенных по форме изолируемой конструкции.","attributes":{}},{"type":"paragraph","content":"","attributes":{}},{"type":"subtitle","content":"7. Антикоррозийная защита","attributes":{}},{"type":"link","content":"","attributes":{"href":null}},{"type":"paragraph","content":"Различают такие основные виды антикоррозийной защиты: футеровку, гуммирование, газопламенное напыление, гидрофобизацию, металлизацию.","attributes":{}},{"type":"paragraph","content":"Футеровка выполняется штучным материалом - кирпичом, каменным литьем и т.д.","attributes":{}},{"type":"paragraph","content":"Отличается от обычной кладки тем, что она обладает значительно более высокой плотностью.","attributes":{}},{"type":"paragraph","content":"Большое внимание уделяют устройству подстилающих слоев под футеровку, обеспечивающих повышенную плотность и химическую стойкость покрытия.","attributes":{}},{"type":"paragraph","content":"Делают их из обмазочной или окрасочной изоляции, а при более агрессивных средах применяют оклеечную изоляцию.","attributes":{}},{"type":"paragraph","content":"Кислотоупорные бетоны - используемые для футеровки, укладывают также, как и обычные. Особенно высокую герметичность футеровочные бетонные покрытия приобретают после наклеивания на их поверхность листов винипласта.","attributes":{}},{"type":"paragraph","content":"Гуммирование поверхностей осуществляется сырой рулонной резиной, резиновым каучуком, синтетическим каучуком, нейритом и тиоколовым герметиком с последующей вулканизацией покрытия. Гуммирование сырой резиной: очищают и обезжиривают поверхность, сначала грунтуют, т.е. наносят на нее тонкий слой резинового клея, затем покрывают рулонной сырой резиной и подвергают тепловой обработке (вулканизируют). Резина при этом образует сплошное покрытие толщиной2-4 мм.","attributes":{}},{"type":"paragraph","content":"Газопламенное напыление - производят порошкообразным термопластом, который наносятна поверхность, нагретую до + 100о , + 180° С,специальной форсункой через воздушно - ацетиленовое пламя под давлением сжатого воздуха. Порошок термопласта при этом расплавляется и при ударе о поверхность уплотняется, образуя сплошное покрытие. Напыление делают тонкими слоями с интервалами 20—40 минут.","attributes":{}},{"type":"paragraph","content":"Гидрофобизацию  -  применяют для защиты бетонных, железобетонных и оштукатуренных поверхностей от воздействия влаги. Для этого используют чаще всего кремнийорганическую эмульсию, которая после высыхания образует прочную водостойкую пленку. Гидрофобный водный раствор наносят краскораспылителем в два три слоя с небольшими перерывами.","attributes":{}},{"type":"paragraph","content":"Флюатирование - выполняют растворами магниевых флюатов с помощью распылителей (до прекращения впитывания).","attributes":{}},{"type":"paragraph","content":"Металлизация - заключается в нанесении антикоррозийного покрытия на предварительно подогреваемую поверхность стальных изделий распылением расплавленного цинка или алюминия струей воздуха.","attributes":{}},{"type":"paragraph","content":"","attributes":{}},{"type":"subtitle","content":"8. Тепло- и звукоизоляция конструкций","attributes":{}},{"type":"link","content":"","attributes":{"href":null}},{"type":"paragraph","content":"Теплоизоляция различных ограждающих конструкций предназначена для обеспечения заданных тепловых режимов зданий, сооружений, установок, трубопроводов.","attributes":{}},{"type":"paragraph","content":"Тепловые режимы могут иметь разное назначение:","attributes":{}},{"type":"paragraph","content":"- для уменьшения тепловых потерь ограждающими строительными конструкциями;","attributes":{}},{"type":"paragraph","content":"- для обеспечения нормального технологического процесса внутри холодильников, специальных складов и т.д.","attributes":{}},{"type":"paragraph","content":"Ужесточение требований по строительной теплотехнике, по повышению теплозащитных свойств зданий требуют кардинальных решений по резкому повышению сопротивления теплопередаче ограждающих конструкций.","attributes":{}},{"type":"paragraph","content":"Повысить теплоизоляционные свойства наружных стен можно несколькими способами: утеплить их снаружи, заложить теплоизоляцию в толщу стены, утеплить с внутренней стороны или возводить конструкции из теплоизоляционно-конструкционных материалов","attributes":{}},{"type":"image","content":"","attributes":{"src":"/default/fast_download/page_images.image_big.8464d038b9cff86e.312e6a7067.jpg"}},{"type":"paragraph","content":"Теплоизоляционные материалы для оборудования и трубопроводов должны иметь γ ≤ 400-500 кг/м3, а для ограждающих конструкций зданий γ < 700 кг/м3.","attributes":{}},{"type":"paragraph","content":"Кроме того материалам должна быть свойственна высокая огне- и температуроустойчивость, механическая прочность, низкая водопоглащаемость, биостойкость, антикоррозийность, воздухо- и газоводонепроницаемость.","attributes":{}},{"type":"paragraph","content":"Как и все материалы и конструкции они должны быть индустриальными и экономичными.","attributes":{}},{"type":"paragraph","content":"Все теплоизоляционные покрытия состоят из таких элементов: антикоррозийного слоя, предохраняющего изолированные поверхности от действия агрессивной среды; теплоизоляционного слоя; деталей крепления - каркаса, сетки, шпилек, бандажей и т.п.;покровного защитного слоя, предохраняющего изоляцию от механических повреждений; паро- и гидроизоляционного слоев, предохраняющих от увлажнения; оклейки, обшивки, окраски, увеличивающихмеханическую прочность изоляции и придающих ей нужный цвет и хороший внешний вид.","attributes":{}},{"type":"paragraph","content":"По способу и технологии монтажа теплоизоляционные покрытия делят на:","attributes":{}},{"type":"paragraph","content":"- засыпные;","attributes":{}},{"type":"paragraph","content":"- мастичные;","attributes":{}},{"type":"paragraph","content":"- литые;","attributes":{}},{"type":"paragraph","content":"- обволакивающие;","attributes":{}},{"type":"paragraph","content":"- сборно-блочные;","attributes":{}},{"type":"paragraph","content":"- вакуумные.","attributes":{}},{"type":"paragraph","content":"Поверхность сначала готовят: чистят от грязи и раковины, устанавливают  крепежные детали, затем наносят изоляцию и защитный слой.","attributes":{}},{"type":"paragraph","content":"Засыпную изоляцию устраивают по горячим и холодным поверхностям.","attributes":{}},{"type":"paragraph","content":"Для засыпки используют волокнистые, порошкообразные и зернистые материалы – минеральную и стеклянную вату, пенопласт, вспученные перлит и вермикулит, пемзу, шлаки, золы.","attributes":{}},{"type":"paragraph","content":"Если вышерасположенными конструкциями теплоизоляция изолирована от атмосферных воздействий, то поверх ее достаточно выполнить защитное покрытие – слой цементно-песчаной или асфальтовой стяжки.","attributes":{}},{"type":"paragraph","content":"Достоинства – простота устройства, малая трудоемкость, низкая стоимость.","attributes":{}},{"type":"paragraph","content":"Недостатки – малая механическая прочность, малая сопротивляемость вибрации, оседание изоляции со временем и оголение верхних слоев.","attributes":{}},{"type":"paragraph","content":"Данный тип изоляции обычно используют для изоляции трубопроводов с горячими и холодными поверхностями.","attributes":{}},{"type":"paragraph","content":"Для получения качественной изоляции необходимо, чтобы изолируемые поверхности имели свою рабочую температуру.","attributes":{}},{"type":"paragraph","content":"Мастики приготавливают из асбозурита, новоасбозурита, асботрепела, совелита, ньювеля и других порошкообразных, зернистых и волокнистых материалов.","attributes":{}},{"type":"paragraph","content":"Мастики должны быть однородны, пористы и пластичны.","attributes":{}},{"type":"paragraph","content":"Мастику наносят на сетки из проволоки в несколько слоев.","attributes":{}},{"type":"paragraph","content":"Мастику можно наносить как вручную, так и с использованием пневмонагнетателей.","attributes":{}},{"type":"paragraph","content":"После полного высыхания изоляцию оклеивают тканью и окрашивают.","attributes":{}},{"type":"paragraph","content":"Достоинства: простота устройства, монолитность, возможность производить работы на поверхностях любой конфигурации.","attributes":{}},{"type":"paragraph","content":"Недостатки: большая трудоемкость, длительность производства работ, нестабильность свойств используемых материалов.","attributes":{}},{"type":"paragraph","content":"Литая теплоизоляция предназначена для промышленных печей, холодильников, котлоагрегатов и осуществляют обычно из пенобетонной ячеистой массы.","attributes":{}},{"type":"paragraph","content":"Специальную пеномассу укладывают при горизонтальных поверхностях в опалубку слоями на высоту до 25 см.","attributes":{}},{"type":"paragraph","content":"На выполненное изоляционное покрытие укладывают рогожу, маты, регулярно поливая водой, обеспечивая нормальный температурно-влажностный режим.","attributes":{}},{"type":"paragraph","content":"При вертикальных изолируемых поверхностях пенобетон наносят методом торкретирования по металлической сетке.","attributes":{}},{"type":"paragraph","content":"В результате получают изоляцию заданной толщины и конфигурации, плотно прилегающий к изолируемой поверхности , без трещин, раковин и других дефектов.","attributes":{}},{"type":"paragraph","content":"Работы выполняют при температуре не ниже + 10°С.","attributes":{}},{"type":"paragraph","content":"Процесс схватывания осуществляется в течении 5 суток.","attributes":{}},{"type":"paragraph","content":"Достоинства - простота, монолитность, высокая механическая прочность, пористость.","attributes":{}},{"type":"paragraph","content":"Недостатки - большая продолжительность процесса, невозможность производства при низких температурах.","attributes":{}},{"type":"paragraph","content":"Для данного типа характерно применение гибких материалов и изделий: прошивных матов, минерального войлока, шнура и подобных материалов.","attributes":{}},{"type":"paragraph","content":"Минеральный войлок наматывают путем накалывания и насаживания на шпильки.","attributes":{}},{"type":"paragraph","content":"Покровный слой крепят на те же шпильки.","attributes":{}},{"type":"paragraph","content":"Комбинированную изоляцию выпускают в виде рулонов.","attributes":{}},{"type":"paragraph","content":"Она включает в себя алюминиевую фольгу с наклеенным на нее минеральным войлоком.","attributes":{}},{"type":"paragraph","content":"Достоинство изоляции в том, что она практически не требует дополнительных креплений, благодаря фольге гарантируется толщина защитного слоя в любом месте сечения, имеется возможность наносить изоляцию в несколько слоев.","attributes":{}},{"type":"paragraph","content":"Достоинства – высокая степеньиндустриальности, простота устройства и нанесение на любую поверхность.","attributes":{}},{"type":"paragraph","content":"Недостаток - боится вибрации, непостоянство объема.","attributes":{}},{"type":"paragraph","content":"Выполняют из сборных изделий – блоков, скорлуп, плит, кирпича и т.п., изготовленных на заводах теплоизоляционных материалов.","attributes":{}},{"type":"paragraph","content":"Изделия укладывают с перевязкой на холодные или горячие поверхности насухо или по мастичной подмазке.","attributes":{}},{"type":"paragraph","content":"Изделия крепят проволокой, бандажами, штырями и крючками.","attributes":{}},{"type":"paragraph","content":"После крепления устраивают покровный слой, например, штукатурят, обклеивают и красят.","attributes":{}},{"type":"paragraph","content":"Достоинства – индустриальность, стандартность, сборность, хорошая механическая прочность.","attributes":{}},{"type":"paragraph","content":"Недостатки – многошовность, сложность нанесения на фасонные части.","attributes":{}},{"type":"paragraph","content":"Применяют в установках глубокого холода, аппаратах для хранения и транспортирования дорогостоящих жидкостей (неона, дейтерия, водорода, гелия и др.).","attributes":{}},{"type":"paragraph","content":"Такая изоляция может быть вакуумной, вакуумно-порошковой и вакуумно-многослойной.","attributes":{}},{"type":"paragraph","content":"Основана на использовании малой теплопроводности вакуумированного пространства, заключенного между изолируемой поверхностью и окутывающим ее кожухом.","attributes":{}},{"type":"paragraph","content":"","attributes":{}},{"type":"subtitle","content":"9. Обеспечение звукоизоляции конструкций при возведении и отделке зданий","attributes":{}},{"type":"link","content":"","attributes":{"href":null}},{"type":"paragraph","content":"Одним из важнейших факторов, оказывающих негативное воздействие на нервную систему человека, являются акустические и вибрационные воздействия. Нормативные требования к звукоизоляции регламентированы в СНиП 23-03-2003 \"Защита от шума и кустика\". Эффективная защита помещений от шума предполагает использование специальных материалов, структура которых, способствует поглощению или ослаблению звуковых колебаний.","attributes":{}},{"type":"paragraph","content":"Самое главное требование, высокое качество строительно-монтажных работ с тщательной заделкой всех сопряжений, примыканий, проходов трубопроводов и электропроводки.","attributes":{}},{"type":"paragraph","content":"Особые требования к звукоизоляции помещений предъявляют к: киноконцертным залам, звукозаписывающим студиям и культовым сооружениям","attributes":{}},{"type":"image","content":"","attributes":{"src":"/default/fast_download/page_images.image_big.8464d038b9cff86e.312e6a7067.jpg"}},{"type":"paragraph","content":"","attributes":{}},{"type":"subtitle","content":"10. Особенности производства изоляционных работ в зимних условиях","attributes":{}},{"type":"link","content":"","attributes":{"href":null}},{"type":"paragraph","content":"Технологические требования по производству работ в зимнее время обусловлены в основном физико-механическими свойствами материалов:","attributes":{}},{"type":"paragraph","content":"- асфальтовые мастики подогревают до температуры + 70° - 80ºС;","attributes":{}},{"type":"paragraph","content":"- в помещениях, где производят изоляцию, поддерживают температуру +10°С - + 15°С, а химически-стойкими лаками + 18° - 20°С;","attributes":{}},{"type":"paragraph","content":"- в мастики добавляют ускорители твердения: хлористые соли, сульфат магния, денатурат, этиловый спирт, но они снижают водоустойчивость покрытия;","attributes":{}},{"type":"paragraph","content":"- антикоррозийные покрытия делают только при положительной температуре;","attributes":{}},{"type":"paragraph","content":"- теплоизоляцию выполняют зимой в условиях, исключающих увлажнение , при дожде или снегопаде производство работ запрещено.","attributes":{}},{"type":"paragraph","content":"","attributes":{}},{"type":"subtitle","content":"11. Техника безопасности при изоляционных работах","attributes":{}},{"type":"link","content":"","attributes":{"href":null}},{"type":"paragraph","content":"- нужна специальная спецодежда при изоляционных работах;","attributes":{}},{"type":"paragraph","content":"- горячие мастики носить только в закрытых ведрах и бачках и заполнять на ¾ емкости;","attributes":{}},{"type":"paragraph","content":"- чтобы не попала вода во время варки битумных мастик;","attributes":{}},{"type":"paragraph","content":"- антикоррозийные работы вести в закрытых помещениях, но вещества взрываемы, поэтому исключены металлические инструменты, чтобы случайно не возникла искра;","attributes":{}},{"type":"paragraph","content":"- воздухообмен делают 4-х кратный.","attributes":{}}]}